CHANGELOG
README.txt
development.ini
setup.cfg
setup.py
test.ini
Restin.egg-info/PKG-INFO
Restin.egg-info/SOURCES.txt
Restin.egg-info/dependency_links.txt
Restin.egg-info/entry_points.txt
Restin.egg-info/not-zip-safe
Restin.egg-info/paste_deploy_config.ini_tmpl
Restin.egg-info/paster_plugins.txt
Restin.egg-info/requires.txt
Restin.egg-info/top_level.txt
docs/intro_quick_start
ez_setup/README.txt
ez_setup/__init__.py
restin/__init__.py
restin/websetup.py
restin/config/__init__.py
restin/config/environment.py
restin/config/middleware.py
restin/config/routing.py
restin/controllers/__init__.py
restin/controllers/applications.py
restin/controllers/data.py
restin/controllers/entities.py
restin/controllers/error.py
restin/controllers/model.py
restin/controllers/template.py
restin/docs/index.txt
restin/i18n/__init__.py
restin/lib/__init__.py
restin/lib/app_globals.py
restin/lib/base.py
restin/lib/helpers.py
restin/models/__init__.py
restin/public/images/powered_by.png
restin/public/restler_public/images/powered_by.png
restin/public/restler_public/images/pylons-tower-dark1.png
restin/public/restler_public/stylesheets/restler.css
restin/public/stylesheets/restler.css
restin/templates/defaults/_form.html
restin/templates/defaults/edit.html
restin/templates/defaults/index.html
restin/templates/defaults/layout.html
restin/templates/defaults/new.html
restin/templates/defaults/show.html
restin/templates/model/index.html
restin/tests/__init__.py
restin/tests/test_models.py
restin/tests/functional/__init__.py
restin/tests/functional/test_applications.py
