Metadata-Version: 1.0
Name: Restin
Version: 0.1a0dev-r21
Summary: RESTful admin app for Pylons
Home-page: http://code.google.com/p/restin/
Author: Wyatt L Baldwin, byCycle.org
Author-email: wyatt@byCycle.org
License: MIT
Keywords: web pylons REST admin
Platform: UNKNOWN
Classifier: Development Status :: 3 - Alpha
Classifier: Environment :: Web Environment
Classifier: Framework :: Paste
Classifier: Intended Audience :: Developers
Classifier: License :: OSI Approved :: MIT License
Classifier: Natural Language :: English
Classifier: Programming Language :: Python
